skdaccess/__init__.py
skdaccess/astro/__init__.py
skdaccess/astro/kepler/__init__.py
skdaccess/astro/kepler/data_fetcher.py
skdaccess/astro/kepler/data_wrapper.py
skdaccess/docs/skdaccess_doxygen.pdf
skdaccess/docs/skdaccess_manual.pdf
skdaccess/examples/groundwater_example.py
skdaccess/framework/__init__.py
skdaccess/framework/data_class.py
skdaccess/framework/param_class.py
skdaccess/geo/__init__.py
skdaccess/geo/grace/__init__.py
skdaccess/geo/grace/data_fetcher.py
skdaccess/geo/grace/data_wrapper.py
skdaccess/geo/groundwater/__init__.py
skdaccess/geo/groundwater/data_fetcher.py
skdaccess/geo/groundwater/data_wrapper.py
skdaccess/geo/pbo/__init__.py
skdaccess/geo/pbo/data_fetcher.py
skdaccess/geo/pbo/data_wrapper.py
skdaccess/utilities/__init__.py
skdaccess/utilities/data_util.py
skdaccess/utilities/map_util.py
skdaccess/utilities/pbo_util.py
skdaccess/utilities/trend_util.py
skdaccess-0.9.3.data/scripts/skdaccess
skdaccess-0.9.3.dist-info/DESCRIPTION.rst
skdaccess-0.9.3.dist-info/METADATA
skdaccess-0.9.3.dist-info/RECORD
skdaccess-0.9.3.dist-info/WHEEL
skdaccess-0.9.3.dist-info/metadata.json
skdaccess-0.9.3.dist-info/pbr.json
skdaccess-0.9.3.dist-info/top_level.txt
