Metadata-Version: 2.0
Name: skdaccess
Version: 0.9.3
Summary: Sci-kit Data Access Package for accessing scientific data sets.
Home-page: UNKNOWN
Author: MITHAGI
Author-email: skdaccess@mit.edu
License: UNKNOWN
Platform: UNKNOWN
Classifier: Topic :: Scientific/Engineering
Classifier: Intended Audience :: Science/Research
Classifier: License :: OSI Approved :: MIT License
Classifier: Programming Language :: Python :: 3 :: Only
Requires-Dist: astropy (>=1.1.2)
Requires-Dist: numpy (>=1.10)
Requires-Dist: pandas (>=0.17)
Requires-Dist: scipy
Requires-Dist: setuptools
Requires-Dist: tables
Requires-Dist: tqdm
